{
  "ComponentIndexes": {},
  "ControlUniqueGuids": {},
  "ControlUniqueIds": {
    "Admin_screen": 145,
    "App": 1,
    "Are you interested in an internal movement?_DataCard1": 119,
    "Are you interested in an internal movement?_DataCard2": 214,
    "Button1": 13,
    "Button1_1": 6,
    "Button2": 144,
    "Button3": 245,
    "Button4": 149,
    "Button4_1": 247,
    "Container2": 248,
    "DataCardKey10": 31,
    "DataCardKey11": 36,
    "DataCardKey12": 41,
    "DataCardKey13": 46,
    "DataCardKey14": 51,
    "DataCardKey15": 56,
    "DataCardKey16": 61,
    "DataCardKey18": 66,
    "DataCardKey19": 71,
    "DataCardKey20": 76,
    "DataCardKey21": 81,
    "DataCardKey22": 86,
    "DataCardKey23": 91,
    "DataCardKey24": 96,
    "DataCardKey25": 101,
    "DataCardKey26": 106,
    "DataCardKey27": 111,
    "DataCardKey28": 116,
    "DataCardKey29": 121,
    "DataCardKey30": 126,
    "DataCardKey31": 131,
    "DataCardKey32": 136,
    "DataCardKey33": 141,
    "DataCardKey37": 155,
    "DataCardKey38": 158,
    "DataCardKey39": 161,
    "DataCardKey40": 164,
    "DataCardKey41": 167,
    "DataCardKey42": 170,
    "DataCardKey43": 173,
    "DataCardKey44": 176,
    "DataCardKey45": 179,
    "DataCardKey46": 182,
    "DataCardKey47": 185,
    "DataCardKey48": 188,
    "DataCardKey49": 191,
    "DataCardKey50": 194,
    "DataCardKey51": 197,
    "DataCardKey52": 200,
    "DataCardKey53": 203,
    "DataCardKey54": 206,
    "DataCardKey55": 209,
    "DataCardKey56": 212,
    "DataCardKey57": 215,
    "DataCardKey58": 218,
    "DataCardKey59": 221,
    "DataCardKey60": 224,
    "DataCardKey61": 227,
    "DataCardKey62": 230,
    "DataCardKey8": 21,
    "DataCardKey9": 26,
    "DataCardKey90": 256,
    "DataCardValue10": 32,
    "DataCardValue11": 37,
    "DataCardValue12": 42,
    "DataCardValue13": 47,
    "DataCardValue14": 52,
    "DataCardValue15": 57,
    "DataCardValue16": 62,
    "DataCardValue18": 67,
    "DataCardValue19": 72,
    "DataCardValue20": 77,
    "DataCardValue21": 82,
    "DataCardValue22": 87,
    "DataCardValue23": 92,
    "DataCardValue24": 97,
    "DataCardValue25": 102,
    "DataCardValue26": 107,
    "DataCardValue27": 112,
    "DataCardValue28": 117,
    "DataCardValue29": 122,
    "DataCardValue30": 127,
    "DataCardValue31": 132,
    "DataCardValue32": 137,
    "DataCardValue33": 142,
    "DataCardValue37": 156,
    "DataCardValue38": 159,
    "DataCardValue39": 162,
    "DataCardValue40": 165,
    "DataCardValue41": 168,
    "DataCardValue42": 171,
    "DataCardValue43": 174,
    "DataCardValue44": 177,
    "DataCardValue45": 180,
    "DataCardValue46": 183,
    "DataCardValue47": 186,
    "DataCardValue48": 189,
    "DataCardValue49": 192,
    "DataCardValue50": 195,
    "DataCardValue51": 198,
    "DataCardValue52": 201,
    "DataCardValue53": 204,
    "DataCardValue54": 207,
    "DataCardValue55": 210,
    "DataCardValue56": 213,
    "DataCardValue57": 216,
    "DataCardValue58": 219,
    "DataCardValue59": 222,
    "DataCardValue60": 225,
    "DataCardValue61": 228,
    "DataCardValue62": 231,
    "DataCardValue8": 22,
    "DataCardValue9": 27,
    "DataCardValue90": 257,
    "Employee Id_DataCard1": 29,
    "Employee Id_DataCard2": 160,
    "ErrorMessage10": 53,
    "ErrorMessage11": 58,
    "ErrorMessage13": 63,
    "ErrorMessage14": 68,
    "ErrorMessage15": 73,
    "ErrorMessage16": 78,
    "ErrorMessage17": 83,
    "ErrorMessage18": 88,
    "ErrorMessage19": 93,
    "ErrorMessage20": 98,
    "ErrorMessage21": 103,
    "ErrorMessage22": 108,
    "ErrorMessage23": 113,
    "ErrorMessage24": 118,
    "ErrorMessage25": 123,
    "ErrorMessage26": 128,
    "ErrorMessage27": 133,
    "ErrorMessage28": 138,
    "ErrorMessage29": 143,
    "ErrorMessage4": 23,
    "ErrorMessage5": 28,
    "ErrorMessage59": 258,
    "ErrorMessage6": 33,
    "ErrorMessage7": 38,
    "ErrorMessage8": 43,
    "ErrorMessage9": 48,
    "Explain how it (expected CTC) is rightfully yours! _DataCard1": 109,
    "Explain how it (expected CTC) is rightfully yours! _DataCard2": 208,
    "Form1": 18,
    "Form2": 253,
    "FormViewer1": 153,
    "Gallery1": 232,
    "galleryTemplate1": 233,
    "Have you been on a quest to level up your skills, bag some certifications, or chase down extra training this year? If yes, describe about them in detail. ( Eg: Name & details of the certification)\u00A0_DataCard1": 59,
    "Have you been on a quest to level up your skills, bag some certifications, or chase down extra training this year? If yes, describe about them in detail. ( Eg: Name & details of the certification)\u00A0_DataCard2": 178,
    "Have you given our employee referral program a spin yet?_DataCard1": 129,
    "Have you given our employee referral program a spin yet?_DataCard2": 220,
    "Host": 3,
    "Icon1": 16,
    "Icon1_1": 147,
    "Icon3": 152,
    "Icon5": 148,
    "Icon6": 150,
    "iconCheck1": 251,
    "iconCircle1": 250,
    "If no, let us know why?!_DataCard1": 134,
    "If no, let us know why?!_DataCard2": 223,
    "Image2": 7,
    "Image3": 5,
    "Jeevan Reporting Manager Name_DataCard1": 34,
    "Jeevan Reporting Manager Name_DataCard2": 163,
    "Label1": 10,
    "Label1_1": 17,
    "Label1_2": 146,
    "Label2": 9,
    "Label3": 8,
    "Label4": 11,
    "Label5": 14,
    "Label6": 12,
    "Label7": 249,
    "Let us know about the one star colleague of yours, who helped you be your better version this year_DataCard1": 74,
    "Let us know about the one star colleague of yours, who helped you be your better version this year_DataCard2": 187,
    "Main_screen": 4,
    "Name_DataCard1": 24,
    "Name_DataCard2": 157,
    "NextArrow2": 235,
    "On a scale of one to ten, how blissful are you with your current job situation? _DataCard1": 114,
    "On a scale of one to ten, how blissful are you with your current job situation? _DataCard2": 211,
    "On a scale of one to ten, where do you rate yourself?_DataCard1": 94,
    "On a scale of one to ten, where do you rate yourself?_DataCard2": 199,
    "On the hunt for some on-site action?_DataCard1": 124,
    "On the hunt for some on-site action?_DataCard2": 217,
    "Paint a picture of your career dreams and ambitions._DataCard1": 79,
    "Paint a picture of your career dreams and ambitions._DataCard2": 190,
    "Please mention your current project name\u00A0_DataCard1": 39,
    "Please mention your current project name\u00A0_DataCard2": 166,
    "Please share your feedback about your reporting manager!_DataCard1": 89,
    "Please share your feedback about your reporting manager!_DataCard2": 196,
    "Rate your knowledge and skills relevant to your role_DataCard1": 54,
    "Rate your knowledge and skills relevant to your role_DataCard2": 175,
    "Rate your problem-solving and critical-thinking skills.  _DataCard1": 69,
    "Rate your problem-solving and critical-thinking skills.  _DataCard2": 184,
    "Rectangle2": 234,
    "Reporting Manager Feedback _DataCard2": 229,
    "Reporting Manager Feedback _DataCard3": 254,
    "Screen1": 252,
    "Separator2": 238,
    "Share any hurdles that came your way in your role. How did you overcome them like a champ?_DataCard1": 49,
    "Share any hurdles that came your way in your role. How did you overcome them like a champ?_DataCard2": 172,
    "Share some standout moments or accomplishments from this year that you think deserve a raise._DataCard1": 44,
    "Share some standout moments or accomplishments from this year that you think deserve a raise._DataCard2": 169,
    "Share the names of 5 Jeevanites whom you think exceeded their work expectations this year!!_DataCard1": 64,
    "Share the names of 5 Jeevanites whom you think exceeded their work expectations this year!!_DataCard2": 181,
    "StarVisible10": 50,
    "StarVisible11": 55,
    "StarVisible13": 60,
    "StarVisible14": 65,
    "StarVisible15": 70,
    "StarVisible16": 75,
    "StarVisible17": 80,
    "StarVisible18": 85,
    "StarVisible19": 90,
    "StarVisible20": 95,
    "StarVisible21": 100,
    "StarVisible22": 105,
    "StarVisible23": 110,
    "StarVisible24": 115,
    "StarVisible25": 120,
    "StarVisible26": 125,
    "StarVisible27": 130,
    "StarVisible28": 135,
    "StarVisible29": 140,
    "StarVisible4": 20,
    "StarVisible5": 25,
    "StarVisible59": 255,
    "StarVisible6": 30,
    "StarVisible7": 35,
    "StarVisible8": 40,
    "StarVisible9": 45,
    "Subtitle2": 237,
    "Success_Screen": 246,
    "Team_DataCard1": 139,
    "Team_DataCard2": 226,
    "TextInput1": 151,
    "Title_DataCard3": 19,
    "Title_DataCard5": 154,
    "Title2": 236,
    "User_screen": 15,
    "What can the company do to fuel your career development?_DataCard1": 84,
    "What can the company do to fuel your career development?_DataCard2": 193,
    "What is your current CTC?_DataCard1": 99,
    "What is your current CTC?_DataCard2": 202,
    "What is your expected CTC? _DataCard1": 104,
    "What is your expected CTC? _DataCard2": 205
  },
  "FunctionParamsInvariantScripts": {},
  "FunctionParamsInvariantScriptsOnInstances": {},
  "HeaderLastSavedDateTimeUTC": "05/20/2024 13:02:09",
  "IsLegacyComponentAllowGlobalScopeCase": false,
  "LocalConnectionIDReferences": {
    "fa7faab7-9e2c-4fc3-9f27-cbcaaf032570": "\"/providers/microsoft.powerapps/apis/shared_sharepointonline/connections/6994c005086e48edaf9b3077714e1b1e\""
  },
  "LocalDatabaseReferencesAsEmpty": true,
  "LocalResourceFileNames": {
    "4_pinkish gradient": "58cfba58-df59-4f81-967c-983cd8052a20.png",
    "482088354": "de92cc48-309b-4db3-9c69-4e9f3ce924c7.jpg",
    "596098068": "3483951e-88e1-4d59-abb8-c3ecefc237e9.jpg",
    "596098068_1": "aa9f10d7-8032-4c94-b38b-7cfad4e7ba4f.jpg",
    "5fc1c59b4fd94ddd8128": "6cc26ebe-3ef8-4669-baa0-a2fb5a0bd986.jpg",
    "download": "ff238b11-e5b6-40bc-9e4d-ae34590e7931.jpg",
    "footer-logo": "f9007676-1df2-43d7-b090-c856eeb57237.png",
    "logo": "9c2c5778-49db-4b54-9523-e818dbcca1e0.png",
    "logo-colour-1": "8c4aeb9e-2447-44ba-ab66-37629191f8ef.png",
    "picccs": "031cdeca-4d52-46b3-ba13-defbacdb9daf.jpg",
    "pngtree-transparent-shape-blue-background-with-circle-in-corner-image_983023": "5da5dcfb-b3b7-4a20-84a9-75dde2dbe673.jpg",
    "yellow-and-blue-background-bqfg6r5bom6fxrvm": "253de4c2-8a83-414e-9b9e-f6c9053697db.jpg"
  },
  "LocalResourceRootPaths": {
    "4_pinkish gradient": "https://docserverpwaprodcin.blob.core.windows.net/6a213d3b-131a-414f-b963-5246be273a92-1/resource/Assets0Images058cfba58-df59-4f81-967c-983cd8052a20.png?skoid=58690ece-ec83-4ce2-9ce8-883d4d6a54ee&sktid=975f013f-7f24-47e8-a7d3-abc4752bf346&skt=2024-05-20T12%3A25%3A48Z&ske=2024-05-21T12%3A40%3A48Z&sks=b&skv=2023-01-03&sv=2023-01-03&spr=https&se=2024-05-21T12%3A40%3A48Z&sr=b&sp=r&sig=8FZeRlepnDowX0W%2FTvZ%2Bkkcp5EBc%2FjwHYGJVjOYWEKI%3D",
    "482088354": "https://docserverpwaprodcin.blob.core.windows.net/6a213d3b-131a-414f-b963-5246be273a92-1/resource/Assets0Images0de92cc48-309b-4db3-9c69-4e9f3ce924c7.jpg?skoid=58690ece-ec83-4ce2-9ce8-883d4d6a54ee&sktid=975f013f-7f24-47e8-a7d3-abc4752bf346&skt=2024-05-20T12%3A25%3A48Z&ske=2024-05-21T12%3A40%3A48Z&sks=b&skv=2023-01-03&sv=2023-01-03&spr=https&se=2024-05-21T12%3A40%3A48Z&sr=b&sp=r&sig=y%2BrhL%2F%2FNM2KL0Y4hNs0keJ%2FSQcIEeHIVGz%2FY9Mf9y4k%3D",
    "596098068": "https://docserverpwaprodcin.blob.core.windows.net/6a213d3b-131a-414f-b963-5246be273a92-1/resource/Assets0Images03483951e-88e1-4d59-abb8-c3ecefc237e9.jpg?skoid=58690ece-ec83-4ce2-9ce8-883d4d6a54ee&sktid=975f013f-7f24-47e8-a7d3-abc4752bf346&skt=2024-05-20T12%3A25%3A48Z&ske=2024-05-21T12%3A40%3A48Z&sks=b&skv=2023-01-03&sv=2023-01-03&spr=https&se=2024-05-21T12%3A40%3A48Z&sr=b&sp=r&sig=9njE6sXjdpUX6BvGUMtWi8uFIjKJ2wJFLHJAeix3%2F%2B4%3D",
    "596098068_1": "https://docserverpwaprodcin.blob.core.windows.net/6a213d3b-131a-414f-b963-5246be273a92-1/resource/Assets0Images0aa9f10d7-8032-4c94-b38b-7cfad4e7ba4f.jpg?skoid=58690ece-ec83-4ce2-9ce8-883d4d6a54ee&sktid=975f013f-7f24-47e8-a7d3-abc4752bf346&skt=2024-05-20T12%3A25%3A48Z&ske=2024-05-21T12%3A40%3A48Z&sks=b&skv=2023-01-03&sv=2023-01-03&spr=https&se=2024-05-21T12%3A40%3A48Z&sr=b&sp=r&sig=6ho4fUtfv297tIGTBDwT4qNuzp7YagOLYl1HROdJQP0%3D",
    "5fc1c59b4fd94ddd8128": "https://docserverpwaprodcin.blob.core.windows.net/6a213d3b-131a-414f-b963-5246be273a92-1/resource/Assets0Images06cc26ebe-3ef8-4669-baa0-a2fb5a0bd986.jpg?skoid=58690ece-ec83-4ce2-9ce8-883d4d6a54ee&sktid=975f013f-7f24-47e8-a7d3-abc4752bf346&skt=2024-05-20T12%3A25%3A48Z&ske=2024-05-21T12%3A40%3A48Z&sks=b&skv=2023-01-03&sv=2023-01-03&spr=https&se=2024-05-21T12%3A40%3A48Z&sr=b&sp=r&sig=BSZJIYwfXRMtgmxm8JaiyD3xLQ5eCwK%2F2%2FkWz8ok54g%3D",
    "download": "https://docserverpwaprodcin.blob.core.windows.net/6a213d3b-131a-414f-b963-5246be273a92-1/resource/Assets0Images0ff238b11-e5b6-40bc-9e4d-ae34590e7931.jpg?skoid=58690ece-ec83-4ce2-9ce8-883d4d6a54ee&sktid=975f013f-7f24-47e8-a7d3-abc4752bf346&skt=2024-05-20T12%3A25%3A48Z&ske=2024-05-21T12%3A40%3A48Z&sks=b&skv=2023-01-03&sv=2023-01-03&spr=https&se=2024-05-21T12%3A40%3A48Z&sr=b&sp=r&sig=k%2BNBICvi439x1TuoX6MygGR8DJMP0VqqcKP5ucBzoi0%3D",
    "footer-logo": "https://docserverpwaprodcin.blob.core.windows.net/6a213d3b-131a-414f-b963-5246be273a92-1/resource/Assets0Images0f9007676-1df2-43d7-b090-c856eeb57237.png?skoid=58690ece-ec83-4ce2-9ce8-883d4d6a54ee&sktid=975f013f-7f24-47e8-a7d3-abc4752bf346&skt=2024-05-20T12%3A25%3A48Z&ske=2024-05-21T12%3A40%3A48Z&sks=b&skv=2023-01-03&sv=2023-01-03&spr=https&se=2024-05-21T12%3A40%3A48Z&sr=b&sp=r&sig=da9T2QcKhG8WTkkt%2BUKeEFdW%2BcLzZSWYcEOBRfKVE%2Fg%3D",
    "logo": "https://docserverpwaprodcin.blob.core.windows.net/6a213d3b-131a-414f-b963-5246be273a92-1/resource/Assets0Images09c2c5778-49db-4b54-9523-e818dbcca1e0.png?skoid=58690ece-ec83-4ce2-9ce8-883d4d6a54ee&sktid=975f013f-7f24-47e8-a7d3-abc4752bf346&skt=2024-05-20T12%3A25%3A48Z&ske=2024-05-21T12%3A40%3A48Z&sks=b&skv=2023-01-03&sv=2023-01-03&spr=https&se=2024-05-21T12%3A40%3A48Z&sr=b&sp=r&sig=b8dOaGctfGTsHFCM5JziMLW3hATBxEfOqxEzOca9Nzc%3D",
    "logo-colour-1": "https://docserverpwaprodcin.blob.core.windows.net/6a213d3b-131a-414f-b963-5246be273a92-1/resource/c3f8802b-f867-4244-95bc-e6df290306ff.png?skoid=58690ece-ec83-4ce2-9ce8-883d4d6a54ee&sktid=975f013f-7f24-47e8-a7d3-abc4752bf346&skt=2024-05-20T12%3A27%3A33Z&ske=2024-05-21T12%3A42%3A33Z&sks=b&skv=2023-01-03&sv=2023-01-03&spr=https&se=2024-05-21T12%3A42%3A33Z&sr=b&sp=r&sig=gDw%2BRgG%2Bv3aDSkup%2F9uHaWEMt7nSnPFzmG7ZXct4PBc%3D",
    "picccs": "https://docserverpwaprodcin.blob.core.windows.net/6a213d3b-131a-414f-b963-5246be273a92-1/resource/7133c536-1d3d-4403-8bfc-a5cfd2b741c1.jpg?skoid=58690ece-ec83-4ce2-9ce8-883d4d6a54ee&sktid=975f013f-7f24-47e8-a7d3-abc4752bf346&skt=2024-05-20T12%3A37%3A26Z&ske=2024-05-21T12%3A52%3A26Z&sks=b&skv=2023-01-03&sv=2023-01-03&spr=https&se=2024-05-21T12%3A52%3A26Z&sr=b&sp=r&sig=QKEyUZms4CmUm74MBe6Y2bxh6BD3HVXdAB79VV8t2Kk%3D",
    "pngtree-transparent-shape-blue-background-with-circle-in-corner-image_983023": "https://docserverpwaprodcin.blob.core.windows.net/6a213d3b-131a-414f-b963-5246be273a92-1/resource/Assets0Images05da5dcfb-b3b7-4a20-84a9-75dde2dbe673.jpg?skoid=58690ece-ec83-4ce2-9ce8-883d4d6a54ee&sktid=975f013f-7f24-47e8-a7d3-abc4752bf346&skt=2024-05-20T12%3A25%3A48Z&ske=2024-05-21T12%3A40%3A48Z&sks=b&skv=2023-01-03&sv=2023-01-03&spr=https&se=2024-05-21T12%3A40%3A48Z&sr=b&sp=r&sig=mXNhaYKvw5GFLm4YFfQulYHJ8dlxsyFafGU5KbGFPHM%3D",
    "yellow-and-blue-background-bqfg6r5bom6fxrvm": "https://docserverpwaprodcin.blob.core.windows.net/6a213d3b-131a-414f-b963-5246be273a92-1/resource/Assets0Images0253de4c2-8a83-414e-9b9e-f6c9053697db.jpg?skoid=58690ece-ec83-4ce2-9ce8-883d4d6a54ee&sktid=975f013f-7f24-47e8-a7d3-abc4752bf346&skt=2024-05-20T12%3A25%3A48Z&ske=2024-05-21T12%3A40%3A48Z&sks=b&skv=2023-01-03&sv=2023-01-03&spr=https&se=2024-05-21T12%3A40%3A48Z&sr=b&sp=r&sig=50TXRD2IN2mZ7Ym5B9bMdNzO7vNyrUc5QUZkg84ockA%3D"
  },
  "OrderComponentMetadata": {},
  "OrderComponentTemplate": {},
  "OrderDataSource": {
    "AppraisalAdminList": 2,
    "AppraisalUserList": 3,
    "ComboBoxSample": 0,
    "CustomGallerySample": 1
  },
  "OrderGroupControls": {},
  "OrderPcfTemplate": {},
  "OrderTemplate": {},
  "OrderXMLTemplate": {
    "button": 1,
    "circle": 10,
    "form": 4,
    "formViewer": 6,
    "gallery": 7,
    "groupContainer": 9,
    "icon": 3,
    "image": 0,
    "label": 2,
    "rectangle": 8,
    "text": 5
  },
  "OverridablePropertiesEntry": {
    "Admin_screen": {},
    "App": {},
    "Are you interested in an internal movement?_DataCard1": {},
    "Are you interested in an internal movement?_DataCard2": {},
    "Button1": {},
    "Button1_1": {},
    "Button2": {},
    "Button3": {},
    "Button4": {},
    "Button4_1": {},
    "Container2": {},
    "DataCardKey10": {},
    "DataCardKey11": {},
    "DataCardKey12": {},
    "DataCardKey13": {},
    "DataCardKey14": {},
    "DataCardKey15": {},
    "DataCardKey16": {},
    "DataCardKey18": {},
    "DataCardKey19": {},
    "DataCardKey20": {},
    "DataCardKey21": {},
    "DataCardKey22": {},
    "DataCardKey23": {},
    "DataCardKey24": {},
    "DataCardKey25": {},
    "DataCardKey26": {},
    "DataCardKey27": {},
    "DataCardKey28": {},
    "DataCardKey29": {},
    "DataCardKey30": {},
    "DataCardKey31": {},
    "DataCardKey32": {},
    "DataCardKey33": {},
    "DataCardKey37": {},
    "DataCardKey38": {},
    "DataCardKey39": {},
    "DataCardKey40": {},
    "DataCardKey41": {},
    "DataCardKey42": {},
    "DataCardKey43": {},
    "DataCardKey44": {},
    "DataCardKey45": {},
    "DataCardKey46": {},
    "DataCardKey47": {},
    "DataCardKey48": {},
    "DataCardKey49": {},
    "DataCardKey50": {},
    "DataCardKey51": {},
    "DataCardKey52": {},
    "DataCardKey53": {},
    "DataCardKey54": {},
    "DataCardKey55": {},
    "DataCardKey56": {},
    "DataCardKey57": {},
    "DataCardKey58": {},
    "DataCardKey59": {},
    "DataCardKey60": {},
    "DataCardKey61": {},
    "DataCardKey62": {},
    "DataCardKey8": {},
    "DataCardKey9": {},
    "DataCardKey90": {},
    "DataCardValue10": {},
    "DataCardValue11": {},
    "DataCardValue12": {},
    "DataCardValue13": {},
    "DataCardValue14": {},
    "DataCardValue15": {},
    "DataCardValue16": {},
    "DataCardValue18": {},
    "DataCardValue19": {},
    "DataCardValue20": {},
    "DataCardValue21": {},
    "DataCardValue22": {},
    "DataCardValue23": {},
    "DataCardValue24": {},
    "DataCardValue25": {},
    "DataCardValue26": {},
    "DataCardValue27": {},
    "DataCardValue28": {},
    "DataCardValue29": {},
    "DataCardValue30": {},
    "DataCardValue31": {},
    "DataCardValue32": {},
    "DataCardValue33": {},
    "DataCardValue37": {},
    "DataCardValue38": {},
    "DataCardValue39": {},
    "DataCardValue40": {},
    "DataCardValue41": {},
    "DataCardValue42": {},
    "DataCardValue43": {},
    "DataCardValue44": {},
    "DataCardValue45": {},
    "DataCardValue46": {},
    "DataCardValue47": {},
    "DataCardValue48": {},
    "DataCardValue49": {},
    "DataCardValue50": {},
    "DataCardValue51": {},
    "DataCardValue52": {},
    "DataCardValue53": {},
    "DataCardValue54": {},
    "DataCardValue55": {},
    "DataCardValue56": {},
    "DataCardValue57": {},
    "DataCardValue58": {},
    "DataCardValue59": {},
    "DataCardValue60": {},
    "DataCardValue61": {},
    "DataCardValue62": {},
    "DataCardValue8": {},
    "DataCardValue9": {},
    "DataCardValue90": {},
    "Employee Id_DataCard1": {},
    "Employee Id_DataCard2": {},
    "ErrorMessage10": {},
    "ErrorMessage11": {},
    "ErrorMessage13": {},
    "ErrorMessage14": {},
    "ErrorMessage15": {},
    "ErrorMessage16": {},
    "ErrorMessage17": {},
    "ErrorMessage18": {},
    "ErrorMessage19": {},
    "ErrorMessage20": {},
    "ErrorMessage21": {},
    "ErrorMessage22": {},
    "ErrorMessage23": {},
    "ErrorMessage24": {},
    "ErrorMessage25": {},
    "ErrorMessage26": {},
    "ErrorMessage27": {},
    "ErrorMessage28": {},
    "ErrorMessage29": {},
    "ErrorMessage4": {},
    "ErrorMessage5": {},
    "ErrorMessage59": {},
    "ErrorMessage6": {},
    "ErrorMessage7": {},
    "ErrorMessage8": {},
    "ErrorMessage9": {},
    "Explain how it (expected CTC) is rightfully yours! _DataCard1": {},
    "Explain how it (expected CTC) is rightfully yours! _DataCard2": {},
    "Form1": {},
    "Form2": {},
    "FormViewer1": {},
    "Gallery1": {},
    "galleryTemplate1": {},
    "Have you been on a quest to level up your skills, bag some certifications, or chase down extra training this year? If yes, describe about them in detail. ( Eg: Name & details of the certification)\u00A0_DataCard1": {},
    "Have you been on a quest to level up your skills, bag some certifications, or chase down extra training this year? If yes, describe about them in detail. ( Eg: Name & details of the certification)\u00A0_DataCard2": {},
    "Have you given our employee referral program a spin yet?_DataCard1": {},
    "Have you given our employee referral program a spin yet?_DataCard2": {},
    "Host": {},
    "Icon1": {},
    "Icon1_1": {},
    "Icon3": {},
    "Icon5": {},
    "Icon6": {},
    "iconCheck1": {},
    "iconCircle1": {},
    "If no, let us know why?!_DataCard1": {},
    "If no, let us know why?!_DataCard2": {},
    "Image2": {},
    "Image3": {},
    "Jeevan Reporting Manager Name_DataCard1": {},
    "Jeevan Reporting Manager Name_DataCard2": {},
    "Label1": {},
    "Label1_1": {},
    "Label1_2": {},
    "Label2": {},
    "Label3": {},
    "Label4": {},
    "Label5": {},
    "Label6": {},
    "Label7": {},
    "Let us know about the one star colleague of yours, who helped you be your better version this year_DataCard1": {},
    "Let us know about the one star colleague of yours, who helped you be your better version this year_DataCard2": {},
    "Main_screen": {},
    "Name_DataCard1": {},
    "Name_DataCard2": {},
    "NextArrow2": {},
    "On a scale of one to ten, how blissful are you with your current job situation? _DataCard1": {},
    "On a scale of one to ten, how blissful are you with your current job situation? _DataCard2": {},
    "On a scale of one to ten, where do you rate yourself?_DataCard1": {},
    "On a scale of one to ten, where do you rate yourself?_DataCard2": {},
    "On the hunt for some on-site action?_DataCard1": {},
    "On the hunt for some on-site action?_DataCard2": {},
    "Paint a picture of your career dreams and ambitions._DataCard1": {},
    "Paint a picture of your career dreams and ambitions._DataCard2": {},
    "Please mention your current project name\u00A0_DataCard1": {},
    "Please mention your current project name\u00A0_DataCard2": {},
    "Please share your feedback about your reporting manager!_DataCard1": {},
    "Please share your feedback about your reporting manager!_DataCard2": {},
    "Rate your knowledge and skills relevant to your role_DataCard1": {},
    "Rate your knowledge and skills relevant to your role_DataCard2": {},
    "Rate your problem-solving and critical-thinking skills.  _DataCard1": {},
    "Rate your problem-solving and critical-thinking skills.  _DataCard2": {},
    "Rectangle2": {},
    "Reporting Manager Feedback _DataCard2": {},
    "Reporting Manager Feedback _DataCard3": {},
    "Screen1": {},
    "Separator2": {},
    "Share any hurdles that came your way in your role. How did you overcome them like a champ?_DataCard1": {},
    "Share any hurdles that came your way in your role. How did you overcome them like a champ?_DataCard2": {},
    "Share some standout moments or accomplishments from this year that you think deserve a raise._DataCard1": {},
    "Share some standout moments or accomplishments from this year that you think deserve a raise._DataCard2": {},
    "Share the names of 5 Jeevanites whom you think exceeded their work expectations this year!!_DataCard1": {},
    "Share the names of 5 Jeevanites whom you think exceeded their work expectations this year!!_DataCard2": {},
    "StarVisible10": {},
    "StarVisible11": {},
    "StarVisible13": {},
    "StarVisible14": {},
    "StarVisible15": {},
    "StarVisible16": {},
    "StarVisible17": {},
    "StarVisible18": {},
    "StarVisible19": {},
    "StarVisible20": {},
    "StarVisible21": {},
    "StarVisible22": {},
    "StarVisible23": {},
    "StarVisible24": {},
    "StarVisible25": {},
    "StarVisible26": {},
    "StarVisible27": {},
    "StarVisible28": {},
    "StarVisible29": {},
    "StarVisible4": {},
    "StarVisible5": {},
    "StarVisible59": {},
    "StarVisible6": {},
    "StarVisible7": {},
    "StarVisible8": {},
    "StarVisible9": {},
    "Subtitle2": {},
    "Success_Screen": {},
    "Team_DataCard1": {},
    "Team_DataCard2": {},
    "TextInput1": {},
    "Title_DataCard3": {},
    "Title_DataCard5": {},
    "Title2": {},
    "User_screen": {},
    "What can the company do to fuel your career development?_DataCard1": {},
    "What can the company do to fuel your career development?_DataCard2": {},
    "What is your current CTC?_DataCard1": {},
    "What is your current CTC?_DataCard2": {},
    "What is your expected CTC? _DataCard1": {},
    "What is your expected CTC? _DataCard2": {}
  },
  "PCFDynamicSchemaForIRRetrievalEntry": {},
  "PCFTemplateEntry": {},
  "PublishOrderIndices": {
    "Admin_screen": 0,
    "App": 0,
    "Are you interested in an internal movement?_DataCard1": 115,
    "Are you interested in an internal movement?_DataCard2": 209,
    "Button1": 9,
    "Button1_1": 1,
    "Button2": 140,
    "Button3": 240,
    "Button4": 144,
    "Button4_1": 241,
    "Container2": 242,
    "DataCardKey10": 27,
    "DataCardKey11": 32,
    "DataCardKey12": 37,
    "DataCardKey13": 42,
    "DataCardKey14": 47,
    "DataCardKey15": 52,
    "DataCardKey16": 57,
    "DataCardKey18": 62,
    "DataCardKey19": 67,
    "DataCardKey20": 72,
    "DataCardKey21": 77,
    "DataCardKey22": 82,
    "DataCardKey23": 87,
    "DataCardKey24": 92,
    "DataCardKey25": 97,
    "DataCardKey26": 102,
    "DataCardKey27": 107,
    "DataCardKey28": 112,
    "DataCardKey29": 117,
    "DataCardKey30": 122,
    "DataCardKey31": 127,
    "DataCardKey32": 132,
    "DataCardKey33": 137,
    "DataCardKey37": 150,
    "DataCardKey38": 153,
    "DataCardKey39": 156,
    "DataCardKey40": 159,
    "DataCardKey41": 162,
    "DataCardKey42": 165,
    "DataCardKey43": 168,
    "DataCardKey44": 171,
    "DataCardKey45": 174,
    "DataCardKey46": 177,
    "DataCardKey47": 180,
    "DataCardKey48": 183,
    "DataCardKey49": 186,
    "DataCardKey50": 189,
    "DataCardKey51": 192,
    "DataCardKey52": 195,
    "DataCardKey53": 198,
    "DataCardKey54": 201,
    "DataCardKey55": 204,
    "DataCardKey56": 207,
    "DataCardKey57": 210,
    "DataCardKey58": 213,
    "DataCardKey59": 216,
    "DataCardKey60": 219,
    "DataCardKey61": 222,
    "DataCardKey62": 225,
    "DataCardKey8": 17,
    "DataCardKey9": 22,
    "DataCardKey90": 237,
    "DataCardValue10": 28,
    "DataCardValue11": 33,
    "DataCardValue12": 38,
    "DataCardValue13": 43,
    "DataCardValue14": 48,
    "DataCardValue15": 53,
    "DataCardValue16": 58,
    "DataCardValue18": 63,
    "DataCardValue19": 68,
    "DataCardValue20": 73,
    "DataCardValue21": 78,
    "DataCardValue22": 83,
    "DataCardValue23": 88,
    "DataCardValue24": 93,
    "DataCardValue25": 98,
    "DataCardValue26": 103,
    "DataCardValue27": 108,
    "DataCardValue28": 113,
    "DataCardValue29": 118,
    "DataCardValue30": 123,
    "DataCardValue31": 128,
    "DataCardValue32": 133,
    "DataCardValue33": 138,
    "DataCardValue37": 151,
    "DataCardValue38": 154,
    "DataCardValue39": 157,
    "DataCardValue40": 160,
    "DataCardValue41": 163,
    "DataCardValue42": 166,
    "DataCardValue43": 169,
    "DataCardValue44": 172,
    "DataCardValue45": 175,
    "DataCardValue46": 178,
    "DataCardValue47": 181,
    "DataCardValue48": 184,
    "DataCardValue49": 187,
    "DataCardValue50": 190,
    "DataCardValue51": 193,
    "DataCardValue52": 196,
    "DataCardValue53": 199,
    "DataCardValue54": 202,
    "DataCardValue55": 205,
    "DataCardValue56": 208,
    "DataCardValue57": 211,
    "DataCardValue58": 214,
    "DataCardValue59": 217,
    "DataCardValue60": 220,
    "DataCardValue61": 223,
    "DataCardValue62": 226,
    "DataCardValue8": 18,
    "DataCardValue9": 23,
    "DataCardValue90": 238,
    "Employee Id_DataCard1": 25,
    "Employee Id_DataCard2": 155,
    "ErrorMessage10": 49,
    "ErrorMessage11": 54,
    "ErrorMessage13": 59,
    "ErrorMessage14": 64,
    "ErrorMessage15": 69,
    "ErrorMessage16": 74,
    "ErrorMessage17": 79,
    "ErrorMessage18": 84,
    "ErrorMessage19": 89,
    "ErrorMessage20": 94,
    "ErrorMessage21": 99,
    "ErrorMessage22": 104,
    "ErrorMessage23": 109,
    "ErrorMessage24": 114,
    "ErrorMessage25": 119,
    "ErrorMessage26": 124,
    "ErrorMessage27": 129,
    "ErrorMessage28": 134,
    "ErrorMessage29": 139,
    "ErrorMessage4": 19,
    "ErrorMessage5": 24,
    "ErrorMessage59": 239,
    "ErrorMessage6": 29,
    "ErrorMessage7": 34,
    "ErrorMessage8": 39,
    "ErrorMessage9": 44,
    "Explain how it (expected CTC) is rightfully yours! _DataCard1": 105,
    "Explain how it (expected CTC) is rightfully yours! _DataCard2": 203,
    "Form1": 14,
    "Form2": 234,
    "FormViewer1": 148,
    "Gallery1": 227,
    "galleryTemplate1": 228,
    "Have you been on a quest to level up your skills, bag some certifications, or chase down extra training this year? If yes, describe about them in detail. ( Eg: Name & details of the certification)\u00A0_DataCard1": 55,
    "Have you been on a quest to level up your skills, bag some certifications, or chase down extra training this year? If yes, describe about them in detail. ( Eg: Name & details of the certification)\u00A0_DataCard2": 173,
    "Have you given our employee referral program a spin yet?_DataCard1": 125,
    "Have you given our employee referral program a spin yet?_DataCard2": 215,
    "Host": 0,
    "Icon1": 11,
    "Icon1_1": 142,
    "Icon3": 147,
    "Icon5": 143,
    "Icon6": 145,
    "iconCheck1": 244,
    "iconCircle1": 243,
    "If no, let us know why?!_DataCard1": 130,
    "If no, let us know why?!_DataCard2": 218,
    "Image2": 3,
    "Image3": 0,
    "Jeevan Reporting Manager Name_DataCard1": 30,
    "Jeevan Reporting Manager Name_DataCard2": 158,
    "Label1": 6,
    "Label1_1": 13,
    "Label1_2": 141,
    "Label2": 5,
    "Label3": 4,
    "Label4": 7,
    "Label5": 10,
    "Label6": 8,
    "Label7": 0,
    "Let us know about the one star colleague of yours, who helped you be your better version this year_DataCard1": 70,
    "Let us know about the one star colleague of yours, who helped you be your better version this year_DataCard2": 182,
    "Main_screen": 0,
    "Name_DataCard1": 20,
    "Name_DataCard2": 152,
    "NextArrow2": 230,
    "On a scale of one to ten, how blissful are you with your current job situation? _DataCard1": 110,
    "On a scale of one to ten, how blissful are you with your current job situation? _DataCard2": 206,
    "On a scale of one to ten, where do you rate yourself?_DataCard1": 90,
    "On a scale of one to ten, where do you rate yourself?_DataCard2": 194,
    "On the hunt for some on-site action?_DataCard1": 120,
    "On the hunt for some on-site action?_DataCard2": 212,
    "Paint a picture of your career dreams and ambitions._DataCard1": 75,
    "Paint a picture of your career dreams and ambitions._DataCard2": 185,
    "Please mention your current project name\u00A0_DataCard1": 35,
    "Please mention your current project name\u00A0_DataCard2": 161,
    "Please share your feedback about your reporting manager!_DataCard1": 85,
    "Please share your feedback about your reporting manager!_DataCard2": 191,
    "Rate your knowledge and skills relevant to your role_DataCard1": 50,
    "Rate your knowledge and skills relevant to your role_DataCard2": 170,
    "Rate your problem-solving and critical-thinking skills.  _DataCard1": 65,
    "Rate your problem-solving and critical-thinking skills.  _DataCard2": 179,
    "Rectangle2": 229,
    "Reporting Manager Feedback _DataCard2": 224,
    "Reporting Manager Feedback _DataCard3": 235,
    "Screen1": 0,
    "Separator2": 233,
    "Share any hurdles that came your way in your role. How did you overcome them like a champ?_DataCard1": 45,
    "Share any hurdles that came your way in your role. How did you overcome them like a champ?_DataCard2": 167,
    "Share some standout moments or accomplishments from this year that you think deserve a raise._DataCard1": 40,
    "Share some standout moments or accomplishments from this year that you think deserve a raise._DataCard2": 164,
    "Share the names of 5 Jeevanites whom you think exceeded their work expectations this year!!_DataCard1": 60,
    "Share the names of 5 Jeevanites whom you think exceeded their work expectations this year!!_DataCard2": 176,
    "StarVisible10": 46,
    "StarVisible11": 51,
    "StarVisible13": 56,
    "StarVisible14": 61,
    "StarVisible15": 66,
    "StarVisible16": 71,
    "StarVisible17": 76,
    "StarVisible18": 81,
    "StarVisible19": 86,
    "StarVisible20": 91,
    "StarVisible21": 96,
    "StarVisible22": 101,
    "StarVisible23": 106,
    "StarVisible24": 111,
    "StarVisible25": 116,
    "StarVisible26": 121,
    "StarVisible27": 126,
    "StarVisible28": 131,
    "StarVisible29": 136,
    "StarVisible4": 16,
    "StarVisible5": 21,
    "StarVisible59": 236,
    "StarVisible6": 26,
    "StarVisible7": 31,
    "StarVisible8": 36,
    "StarVisible9": 41,
    "Subtitle2": 232,
    "Success_Screen": 0,
    "Team_DataCard1": 135,
    "Team_DataCard2": 221,
    "TextInput1": 146,
    "Title_DataCard3": 15,
    "Title_DataCard5": 149,
    "Title2": 231,
    "User_screen": 0,
    "What can the company do to fuel your career development?_DataCard1": 80,
    "What can the company do to fuel your career development?_DataCard2": 188,
    "What is your current CTC?_DataCard1": 95,
    "What is your current CTC?_DataCard2": 197,
    "What is your expected CTC? _DataCard1": 100,
    "What is your expected CTC? _DataCard2": 200
  },
  "ResourcesJsonIndices": {
    "Image-4_pinkish gradient": 0,
    "Image-482088354": 4,
    "Image-596098068": 2,
    "Image-596098068_1": 3,
    "Image-5fc1c59b4fd94ddd8128": 8,
    "Image-download": 5,
    "Image-footer-logo": 9,
    "Image-logo": 11,
    "Image-logo-colour-1": 12,
    "Image-picccs": 10,
    "Image-pngtree-transparent-shape-blue-background-with-circle-in-corner-image_983023": 6,
    "Image-SampleImage": 1,
    "Image-yellow-and-blue-background-bqfg6r5bom6fxrvm": 7
  },
  "RuleScreenIdWithoutScreen": {},
  "TemplateVersions": {},
  "VolatileProperties": {
    "AnalysisLoadTime": 1.7352136,
    "ControlCount": {
      "button": 6,
      "circle": 1,
      "form": 3,
      "formViewer": 1,
      "gallery": 1,
      "galleryTemplate": 1,
      "groupContainer": 1,
      "icon": 7,
      "image": 2,
      "label": 144,
      "rectangle": 2,
      "screen": 4,
      "text": 28,
      "typedDataCard": 53
    },
    "DeserializationLoadTime": 2.7824841
  },
  "WasLocalDatabaseReferencesEmpty": true
}